Metadata-Version: 2.4
Name: yyxxdata-warehouse-core
Version: 0.1.2
Summary: 数据处理核心库，提供数据库连接和Ibis数据处理能力
License: MIT
Author: Zeng Kaishin
Author-email: kaishinz@qq.com
Requires-Python: >=3.11,<4.0
Classifier: License :: OSI Approved :: MIT License
Classifier: Programming Language :: Python :: 3
Classifier: Programming Language :: Python :: 3.11
Classifier: Programming Language :: Python :: 3.12
Classifier: Programming Language :: Python :: 3.13
Classifier: Programming Language :: Python :: 3.14
Requires-Dist: atpublic (>=6.0.0,<7.0.0)
Requires-Dist: ibis-framework[mysql,sqlite] (==11.0.0)
Requires-Dist: mysqlclient (>=2.2.7,<3.0.0)
Requires-Dist: pandas (>=2.3.3,<3.0.0)
Requires-Dist: parsy (>=2.0.0,<3.0.0)
Requires-Dist: pyarrow (>=22.0.0,<23.0.0)
Requires-Dist: pyyaml (>=6.0.3,<7.0.0)
Requires-Dist: regex (>=2025.11.3,<2026.0.0)
Requires-Dist: rich (>=14.2.0,<15.0.0)
Requires-Dist: sqlalchemy (>=2.0.44,<3.0.0)
Requires-Dist: sqlglot (>=23.4,!=26.32.0)
Requires-Dist: toolz (>=0.12.0,<0.13.0)
Requires-Dist: typing-extensions (>=4.0.0,<5.0.0)
